{
    "name": "unbarrel",
    "version": "0.3.0",
    "factorio_version": "1.1",
    "title": "Unbarrel",
    "author": "Brevven",
    "contact": "",
    "homepage": "",
    "dependencies": [
      "(?) space-exploration",
      "(?) aai-industry",
      "(?) Krastorio2",
      "(?) bzfoundry",
      "(?) bzaluminum",
      "(?) bzlead",
      "(?) bzcarbon",
      "(?) bztitanium",
      "(?) bzsilicon",
      "(?) bztungsten",
      "(?) bztin",
      "(?) bzzirconium",
      "(?) bz-dsr-bridge",
      "(?) pycoalprocessing",
      "(?) pyfusionenergy",
      "(?) pyfusionenergy",
      "(?) pyindustry",
      "(?) pyhightech",
      "(?) pyrawores",
      "(?) pypetroleumhandling",
      "(?) pycoalprocessinggraphics",
      "(?) pyalienlife",
      "(?) IndustrialRevolution",
      "(?) 248k",
      "(?) deadlock-beltboxes-loaders",
      "(?) DeadlockCrating",

      "base >= 1.1.0"
    ],
    "description": "Hides some recipes from the handcrafting menu. Defaults to barreling and unbarreling recipes\n\nCustomize hidden subgroups, groups, categories, and recipes."
}

